secure_fs/__init__.py
secure_fs-0.1.0.dist-info/LICENSE
secure_fs-0.1.0.dist-info/METADATA
secure_fs-0.1.0.dist-info/WHEEL
secure_fs-0.1.0.dist-info/top_level.txt
secure_fs-0.1.0.dist-info/RECORD
