Metadata-Version: 2.1
Name: secure-fs
Version: 0.1.0
Summary: Library that ensures restrictive file permissions and safe paths when creating and working with files and directories.
Home-page: https://github.com/freedomofpress/secure-fs
Author: Freedom of the Press Foundation
Author-email: securedrop@freedom.press
License: GPLv3+
Platform: UNKNOWN
Classifier: Programming Language :: Python :: 3
Classifier: Topic :: Software Development :: Libraries :: Python Modules
Classifier: License :: OSI Approved :: GNU General Public License v3 or later (GPLv3+)
Classifier: Intended Audience :: Developers
Classifier: Operating System :: OS Independent
Requires-Python: >=3.5
License-File: LICENSE
